{"2026-03":{"total":114,"province":[{"name":"上海","value":25},{"name":"北京","value":23},{"name":"浙江","value":16},{"name":"江苏","value":14},{"name":"四川","value":13},{"name":"重庆","value":12},{"name":"广东","value":11}],"city":[{"province":"上海","name":"上海","value":25},{"province":"北京","name":"北京","value":23},{"province":"浙江","name":"杭州","value":16},{"province":"江苏","name":"苏州","value":14},{"province":"四川","name":"成都","value":13},{"province":"重庆","name":"重庆","value":12},{"province":"广东","name":"深圳","value":11}]},"2026-02":{"total":17,"province":[{"name":"上海","value":17}],"city":[{"province":"上海","name":"上海","value":17}]},"2026-01":{"total":116,"province":[{"name":"江苏","value":29},{"name":"广东","value":27},{"name":"上海","value":22},{"name":"北京","value":15},{"name":"浙江","value":12},{"name":"安徽","value":11}],"city":[{"province":"上海","name":"上海","value":22},{"province":"江苏","name":"苏州","value":16},{"province":"北京","name":"北京","value":15},{"province":"广东","name":"广州","value":14},{"province":"江苏","name":"南京","value":13},{"province":"广东","name":"深圳","value":13},{"province":"浙江","name":"杭州","value":12},{"province":"安徽","name":"合肥","value":11}]},"2025-12":{"total":254,"province":[{"name":"江苏","value":39},{"name":"广东","value":38},{"name":"山东","value":38},{"name":"上海","value":38},{"name":"浙江","value":27},{"name":"四川","value":24},{"name":"福建","value":21},{"name":"北京","value":18},{"name":"天津","value":11}],"city":[{"province":"上海","name":"上海","value":38},{"province":"浙江","name":"杭州","value":27},{"province":"四川","name":"成都","value":24},{"province":"广东","name":"深圳","value":24},{"province":"江苏","name":"苏州","value":22},{"province":"福建","name":"厦门","value":21},{"province":"山东","name":"济南","value":20},{"province":"北京","name":"北京","value":18},{"province":"山东","name":"枣庄","value":18},{"province":"江苏","name":"南京","value":17},{"province":"广东","name":"广州","value":14},{"province":"天津","name":"天津","value":11}]},"2025-11":{"total":282,"province":[{"name":"江苏","value":64},{"name":"广东","value":49},{"name":"浙江","value":42},{"name":"上海","value":33},{"name":"四川","value":33},{"name":"北京","value":25},{"name":"重庆","value":14},{"name":"陕西","value":11},{"name":"云南","value":11}],"city":[{"province":"四川","name":"成都","value":33},{"province":"上海","name":"上海","value":33},{"province":"北京","name":"北京","value":25},{"province":"广东","name":"广州","value":25},{"province":"浙江","name":"杭州","value":24},{"province":"广东","name":"深圳","value":24},{"province":"江苏","name":"无锡","value":23},{"province":"江苏","name":"苏州","value":22},{"province":"江苏","name":"南京","value":19},{"province":"浙江","name":"宁波","value":18},{"province":"重庆","name":"重庆","value":14},{"province":"云南","name":"昆明","value":11},{"province":"陕西","name":"西安","value":11}]},"2025-10":{"total":135,"province":[{"name":"广东","value":34},{"name":"上海","value":28},{"name":"浙江","value":18},{"name":"北京","value":16},{"name":"福建","value":14},{"name":"四川","value":14},{"name":"江苏","value":11}],"city":[{"province":"上海","name":"上海","value":28},{"province":"浙江","name":"杭州","value":18},{"province":"广东","name":"深圳","value":18},{"province":"北京","name":"北京","value":16},{"province":"广东","name":"广州","value":16},{"province":"四川","name":"成都","value":14},{"province":"福建","name":"厦门","value":14},{"province":"江苏","name":"苏州","value":11}]},"2025-09":{"total":176,"province":[{"name":"江苏","value":41},{"name":"广东","value":39},{"name":"四川","value":35},{"name":"上海","value":24},{"name":"北京","value":13},{"name":"湖南","value":13},{"name":"重庆","value":11}],"city":[{"province":"四川","name":"成都","value":35},{"province":"广东","name":"深圳","value":26},{"province":"上海","name":"上海","value":24},{"province":"江苏","name":"南京","value":18},{"province":"北京","name":"北京","value":13},{"province":"广东","name":"广州","value":13},{"province":"湖南","name":"长沙","value":13},{"province":"江苏","name":"苏州","value":12},{"province":"江苏","name":"常州","value":11},{"province":"重庆","name":"重庆","value":11}]},"2025-08":{"total":239,"province":[{"name":"浙江","value":57},{"name":"广东","value":42},{"name":"上海","value":29},{"name":"江苏","value":27},{"name":"四川","value":17},{"name":"云南","value":15},{"name":"北京","value":14},{"name":"重庆","value":14},{"name":"湖北","value":13},{"name":"河南","value":11}],"city":[{"province":"上海","name":"上海","value":29},{"province":"广东","name":"广州","value":22},{"province":"广东","name":"深圳","value":20},{"province":"浙江","name":"杭州","value":19},{"province":"四川","name":"成都","value":17},{"province":"浙江","name":"宁波","value":16},{"province":"江苏","name":"苏州","value":16},{"province":"云南","name":"昆明","value":15},{"province":"北京","name":"北京","value":14},{"province":"重庆","name":"重庆","value":14},{"province":"湖北","name":"武汉","value":13},{"province":"浙江","name":"金华","value":11},{"province":"江苏","name":"南京","value":11},{"province":"浙江","name":"台州","value":11},{"province":"河南","name":"郑州","value":11}]},"2025-07":{"total":165,"province":[{"name":"江苏","value":36},{"name":"浙江","value":27},{"name":"上海","value":23},{"name":"广东","value":16},{"name":"四川","value":15},{"name":"北京","value":14},{"name":"重庆","value":12},{"name":"湖南","value":11},{"name":"陕西","value":11}],"city":[{"province":"上海","name":"上海","value":23},{"province":"广东","name":"深圳","value":16},{"province":"四川","name":"成都","value":15},{"province":"北京","name":"北京","value":14},{"province":"浙江","name":"宁波","value":14},{"province":"江苏","name":"无锡","value":14},{"province":"浙江","name":"杭州","value":13},{"province":"重庆","name":"重庆","value":12},{"province":"江苏","name":"南京","value":11},{"province":"江苏","name":"苏州","value":11},{"province":"陕西","name":"西安","value":11},{"province":"湖南","name":"长沙","value":11}]},"2025-06":{"total":163,"province":[{"name":"江苏","value":32},{"name":"浙江","value":31},{"name":"上海","value":30},{"name":"北京","value":18},{"name":"陕西","value":15},{"name":"四川","value":14},{"name":"广东","value":12},{"name":"湖南","value":11}],"city":[{"province":"上海","name":"上海","value":30},{"province":"江苏","name":"苏州","value":20},{"province":"北京","name":"北京","value":18},{"province":"浙江","name":"杭州","value":17},{"province":"陕西","name":"西安","value":15},{"province":"四川","name":"成都","value":14},{"province":"浙江","name":"宁波","value":14},{"province":"广东","name":"深圳","value":12},{"province":"江苏","name":"无锡","value":12},{"province":"湖南","name":"长沙","value":11}]},"2025-05":{"total":150,"province":[{"name":"北京","value":31},{"name":"江苏","value":26},{"name":"上海","value":26},{"name":"广东","value":22},{"name":"四川","value":17},{"name":"浙江","value":15},{"name":"重庆","value":13}],"city":[{"province":"北京","name":"北京","value":31},{"province":"上海","name":"上海","value":26},{"province":"江苏","name":"苏州","value":26},{"province":"四川","name":"成都","value":17},{"province":"浙江","name":"杭州","value":15},{"province":"重庆","name":"重庆","value":13},{"province":"广东","name":"广州","value":11},{"province":"广东","name":"深圳","value":11}]},"2025-03":{"total":138,"province":[{"name":"浙江","value":27},{"name":"北京","value":25},{"name":"上海","value":25},{"name":"江苏","value":18},{"name":"四川","value":16},{"name":"辽宁","value":14},{"name":"广东","value":13}],"city":[{"province":"北京","name":"北京","value":25},{"province":"上海","name":"上海","value":25},{"province":"江苏","name":"苏州","value":18},{"province":"四川","name":"成都","value":16},{"province":"浙江","name":"杭州","value":16},{"province":"辽宁","name":"沈阳","value":14},{"province":"广东","name":"深圳","value":13},{"province":"浙江","name":"宁波","value":11}]},"2025-02":{"total":66,"province":[{"name":"上海","value":25},{"name":"浙江","value":24},{"name":"四川","value":17}],"city":[{"province":"上海","name":"上海","value":25},{"province":"四川","name":"成都","value":17},{"province":"浙江","name":"宁波","value":13},{"province":"浙江","name":"杭州","value":11}]},"2025-01":{"total":155,"province":[{"name":"浙江","value":45},{"name":"广东","value":37},{"name":"江苏","value":32},{"name":"北京","value":23},{"name":"上海","value":18}],"city":[{"province":"北京","name":"北京","value":23},{"province":"江苏","name":"苏州","value":21},{"province":"上海","name":"上海","value":18},{"province":"浙江","name":"温州","value":18},{"province":"浙江","name":"金华","value":14},{"province":"广东","name":"东莞","value":13},{"province":"广东","name":"广州","value":13},{"province":"浙江","name":"杭州","value":13},{"province":"江苏","name":"南京","value":11},{"province":"广东","name":"深圳","value":11}]},"2024-12":{"total":168,"province":[{"name":"江苏","value":52},{"name":"上海","value":32},{"name":"浙江","value":26},{"name":"北京","value":25},{"name":"湖南","value":11},{"name":"陕西","value":11},{"name":"四川","value":11}],"city":[{"province":"上海","name":"上海","value":32},{"province":"北京","name":"北京","value":25},{"province":"江苏","name":"苏州","value":22},{"province":"江苏","name":"南京","value":16},{"province":"浙江","name":"杭州","value":14},{"province":"江苏","name":"无锡","value":14},{"province":"浙江","name":"宁波","value":12},{"province":"四川","name":"成都","value":11},{"province":"陕西","name":"西安","value":11},{"province":"湖南","name":"长沙","value":11}]},"2024-11":{"total":159,"province":[{"name":"北京","value":32},{"name":"广东","value":29},{"name":"江苏","value":28},{"name":"浙江","value":27},{"name":"上海","value":19},{"name":"四川","value":13},{"name":"湖北","value":11}],"city":[{"province":"北京","name":"北京","value":32},{"province":"上海","name":"上海","value":19},{"province":"浙江","name":"杭州","value":16},{"province":"广东","name":"深圳","value":16},{"province":"江苏","name":"苏州","value":15},{"province":"四川","name":"成都","value":13},{"province":"广东","name":"广州","value":13},{"province":"江苏","name":"南京","value":13},{"province":"浙江","name":"宁波","value":11},{"province":"湖北","name":"武汉","value":11}]},"2024-10":{"total":97,"province":[{"name":"上海","value":34},{"name":"江苏","value":27},{"name":"浙江","value":19},{"name":"北京","value":17}],"city":[{"province":"上海","name":"上海","value":34},{"province":"浙江","name":"杭州","value":19},{"province":"北京","name":"北京","value":17},{"province":"江苏","name":"苏州","value":15},{"province":"江苏","name":"南通","value":12}]},"2024-09":{"total":188,"province":[{"name":"江苏","value":50},{"name":"浙江","value":32},{"name":"广东","value":27},{"name":"上海","value":25},{"name":"北京","value":16},{"name":"吉林","value":14},{"name":"安徽","value":13},{"name":"四川","value":11}],"city":[{"province":"上海","name":"上海","value":25},{"province":"浙江","name":"杭州","value":21},{"province":"江苏","name":"苏州","value":20},{"province":"北京","name":"北京","value":16},{"province":"江苏","name":"无锡","value":16},{"province":"江苏","name":"南京","value":14},{"province":"广东","name":"深圳","value":14},{"province":"吉林","name":"长春","value":14},{"province":"广东","name":"广州","value":13},{"province":"安徽","name":"合肥","value":13},{"province":"四川","name":"成都","value":11},{"province":"浙江","name":"宁波","value":11}]},"2024-07":{"total":143,"province":[{"name":"广东","value":29},{"name":"北京","value":27},{"name":"上海","value":26},{"name":"江苏","value":24},{"name":"浙江","value":24},{"name":"四川","value":13}],"city":[{"province":"北京","name":"北京","value":27},{"province":"上海","name":"上海","value":26},{"province":"广东","name":"广州","value":16},{"province":"四川","name":"成都","value":13},{"province":"广东","name":"深圳","value":13},{"province":"浙江","name":"杭州","value":12},{"province":"江苏","name":"南京","value":12},{"province":"浙江","name":"宁波","value":12},{"province":"江苏","name":"无锡","value":12}]},"2023-11":{"total":12,"province":[{"name":"北京","value":12}],"city":[{"province":"北京","name":"北京","value":12}]},"2023-10":{"total":60,"province":[{"name":"广东","value":26},{"name":"四川","value":12},{"name":"北京","value":11},{"name":"上海","value":11}],"city":[{"province":"广东","name":"广州","value":15},{"province":"四川","name":"成都","value":12},{"province":"北京","name":"北京","value":11},{"province":"上海","name":"上海","value":11},{"province":"广东","name":"深圳","value":11}]},"2023-09":{"total":206,"province":[{"name":"广东","value":53},{"name":"江苏","value":30},{"name":"上海","value":29},{"name":"北京","value":22},{"name":"四川","value":22},{"name":"重庆","value":14},{"name":"浙江","value":13},{"name":"陕西","value":12},{"name":"天津","value":11}],"city":[{"province":"上海","name":"上海","value":29},{"province":"北京","name":"北京","value":22},{"province":"四川","name":"成都","value":22},{"province":"广东","name":"深圳","value":20},{"province":"广东","name":"广州","value":18},{"province":"江苏","name":"苏州","value":16},{"province":"广东","name":"东莞","value":15},{"province":"重庆","name":"重庆","value":14},{"province":"江苏","name":"南京","value":14},{"province":"浙江","name":"杭州","value":13},{"province":"陕西","name":"西安","value":12},{"province":"天津","name":"天津","value":11}]},"2023-08":{"total":242,"province":[{"name":"广东","value":56},{"name":"上海","value":53},{"name":"湖北","value":23},{"name":"北京","value":22},{"name":"江苏","value":22},{"name":"浙江","value":22},{"name":"四川","value":21},{"name":"陕西","value":12},{"name":"重庆","value":11}],"city":[{"province":"上海","name":"上海","value":53},{"province":"广东","name":"广州","value":27},{"province":"湖北","name":"武汉","value":23},{"province":"北京","name":"北京","value":22},{"province":"浙江","name":"杭州","value":22},{"province":"江苏","name":"苏州","value":22},{"province":"四川","name":"成都","value":21},{"province":"广东","name":"深圳","value":16},{"province":"广东","name":"东莞","value":13},{"province":"陕西","name":"西安","value":12},{"province":"重庆","name":"重庆","value":11}]},"2023-07":{"total":259,"province":[{"name":"上海","value":46},{"name":"江苏","value":43},{"name":"浙江","value":32},{"name":"广东","value":29},{"name":"四川","value":20},{"name":"北京","value":19},{"name":"云南","value":17},{"name":"湖南","value":16},{"name":"重庆","value":13},{"name":"福建","value":13},{"name":"河南","value":11}],"city":[{"province":"上海","name":"上海","value":46},{"province":"江苏","name":"苏州","value":26},{"province":"四川","name":"成都","value":20},{"province":"浙江","name":"杭州","value":20},{"province":"北京","name":"北京","value":19},{"province":"云南","name":"昆明","value":17},{"province":"江苏","name":"南京","value":17},{"province":"湖南","name":"长沙","value":16},{"province":"广东","name":"深圳","value":15},{"province":"广东","name":"东莞","value":14},{"province":"重庆","name":"重庆","value":13},{"province":"福建","name":"厦门","value":13},{"province":"浙江","name":"宁波","value":12},{"province":"河南","name":"郑州","value":11}]},"2023-06":{"total":303,"province":[{"name":"江苏","value":60},{"name":"上海","value":50},{"name":"广东","value":48},{"name":"浙江","value":36},{"name":"北京","value":29},{"name":"重庆","value":20},{"name":"四川","value":18},{"name":"福建","value":15},{"name":"湖南","value":14},{"name":"安徽","value":13}],"city":[{"province":"上海","name":"上海","value":50},{"province":"北京","name":"北京","value":29},{"province":"江苏","name":"苏州","value":25},{"province":"浙江","name":"杭州","value":24},{"province":"广东","name":"深圳","value":24},{"province":"重庆","name":"重庆","value":20},{"province":"四川","name":"成都","value":18},{"province":"江苏","name":"无锡","value":18},{"province":"江苏","name":"南京","value":17},{"province":"福建","name":"厦门","value":15},{"province":"湖南","name":"长沙","value":14},{"province":"广东","name":"广州","value":13},{"province":"安徽","name":"合肥","value":13},{"province":"浙江","name":"宁波","value":12},{"province":"广东","name":"佛山","value":11}]},"2023-05":{"total":349,"province":[{"name":"广东","value":63},{"name":"江苏","value":57},{"name":"上海","value":53},{"name":"浙江","value":47},{"name":"北京","value":31},{"name":"四川","value":31},{"name":"重庆","value":18},{"name":"河南","value":13},{"name":"山东","value":13},{"name":"福建","value":12},{"name":"湖北","value":11}],"city":[{"province":"上海","name":"上海","value":53},{"province":"北京","name":"北京","value":31},{"province":"四川","name":"成都","value":31},{"province":"广东","name":"深圳","value":24},{"province":"江苏","name":"苏州","value":24},{"province":"浙江","name":"杭州","value":23},{"province":"广东","name":"广州","value":21},{"province":"重庆","name":"重庆","value":18},{"province":"广东","name":"东莞","value":18},{"province":"江苏","name":"南京","value":18},{"province":"江苏","name":"无锡","value":15},{"province":"山东","name":"青岛","value":13},{"province":"河南","name":"郑州","value":13},{"province":"福建","name":"福州","value":12},{"province":"浙江","name":"宁波","value":12},{"province":"浙江","name":"台州","value":12},{"province":"湖北","name":"武汉","value":11}]},"2023-04":{"total":411,"province":[{"name":"江苏","value":70},{"name":"广东","value":59},{"name":"上海","value":58},{"name":"北京","value":41},{"name":"四川","value":26},{"name":"辽宁","value":22},{"name":"重庆","value":18},{"name":"河南","value":18},{"name":"山东","value":18},{"name":"浙江","value":17},{"name":"湖南","value":16},{"name":"福建","value":13},{"name":"陕西","value":13},{"name":"安徽","value":11},{"name":"湖北","value":11}],"city":[{"province":"上海","name":"上海","value":58},{"province":"北京","name":"北京","value":41},{"province":"广东","name":"深圳","value":30},{"province":"江苏","name":"苏州","value":29},{"province":"四川","name":"成都","value":26},{"province":"江苏","name":"南京","value":24},{"province":"重庆","name":"重庆","value":18},{"province":"山东","name":"青岛","value":18},{"province":"河南","name":"郑州","value":18},{"province":"浙江","name":"杭州","value":17},{"province":"江苏","name":"无锡","value":17},{"province":"湖南","name":"长沙","value":16},{"province":"广东","name":"广州","value":15},{"province":"广东","name":"东莞","value":14},{"province":"福建","name":"厦门","value":13},{"province":"陕西","name":"西安","value":13},{"province":"辽宁","name":"大连","value":11},{"province":"安徽","name":"合肥","value":11},{"province":"辽宁","name":"沈阳","value":11},{"province":"湖北","name":"武汉","value":11}]},"2023-03":{"total":583,"province":[{"name":"浙江","value":104},{"name":"广东","value":81},{"name":"江苏","value":73},{"name":"上海","value":63},{"name":"北京","value":53},{"name":"湖北","value":28},{"name":"湖南","value":28},{"name":"四川","value":28},{"name":"山东","value":24},{"name":"重庆","value":18},{"name":"云南","value":17},{"name":"福建","value":15},{"name":"陕西","value":15},{"name":"江西","value":14},{"name":"河南","value":11},{"name":"天津","value":11}],"city":[{"province":"上海","name":"上海","value":63},{"province":"北京","name":"北京","value":53},{"province":"浙江","name":"杭州","value":41},{"province":"广东","name":"广州","value":31},{"province":"四川","name":"成都","value":28},{"province":"湖北","name":"武汉","value":28},{"province":"湖南","name":"长沙","value":28},{"province":"江苏","name":"苏州","value":27},{"province":"广东","name":"深圳","value":24},{"province":"重庆","name":"重庆","value":18},{"province":"云南","name":"昆明","value":17},{"province":"江苏","name":"南京","value":17},{"province":"福建","name":"厦门","value":15},{"province":"江苏","name":"无锡","value":15},{"province":"陕西","name":"西安","value":15},{"province":"江西","name":"南昌","value":14},{"province":"江苏","name":"南通","value":14},{"province":"浙江","name":"绍兴","value":14},{"province":"广东","name":"东莞","value":13},{"province":"广东","name":"佛山","value":13},{"province":"浙江","name":"金华","value":13},{"province":"浙江","name":"宁波","value":13},{"province":"山东","name":"济南","value":12},{"province":"浙江","name":"嘉兴","value":12},{"province":"山东","name":"青岛","value":12},{"province":"天津","name":"天津","value":11},{"province":"浙江","name":"温州","value":11},{"province":"河南","name":"郑州","value":11}]},"2023-02":{"total":519,"province":[{"name":"浙江","value":92},{"name":"江苏","value":70},{"name":"广东","value":60},{"name":"上海","value":41},{"name":"北京","value":32},{"name":"福建","value":31},{"name":"四川","value":30},{"name":"安徽","value":26},{"name":"湖北","value":24},{"name":"陕西","value":23},{"name":"云南","value":20},{"name":"湖南","value":19},{"name":"重庆","value":17},{"name":"黑龙江","value":12},{"name":"贵州","value":11},{"name":"天津","value":11}],"city":[{"province":"上海","name":"上海","value":41},{"province":"广东","name":"深圳","value":34},{"province":"北京","name":"北京","value":32},{"province":"四川","name":"成都","value":30},{"province":"江苏","name":"南京","value":30},{"province":"江苏","name":"苏州","value":29},{"province":"广东","name":"广州","value":26},{"province":"浙江","name":"杭州","value":26},{"province":"安徽","name":"合肥","value":26},{"province":"湖北","name":"武汉","value":24},{"province":"陕西","name":"西安","value":23},{"province":"浙江","name":"金华","value":20},{"province":"云南","name":"昆明","value":20},{"province":"福建","name":"厦门","value":20},{"province":"湖南","name":"长沙","value":19},{"province":"浙江","name":"宁波","value":18},{"province":"重庆","name":"重庆","value":17},{"province":"浙江","name":"温州","value":16},{"province":"黑龙江","name":"哈尔滨","value":12},{"province":"浙江","name":"绍兴","value":12},{"province":"福建","name":"福州","value":11},{"province":"贵州","name":"贵阳","value":11},{"province":"江苏","name":"南通","value":11},{"province":"天津","name":"天津","value":11}]},"2023-01":{"total":339,"province":[{"name":"浙江","value":73},{"name":"江苏","value":57},{"name":"广东","value":40},{"name":"上海","value":30},{"name":"北京","value":25},{"name":"湖北","value":23},{"name":"四川","value":21},{"name":"湖南","value":16},{"name":"陕西","value":16},{"name":"福建","value":14},{"name":"重庆","value":13},{"name":"吉林","value":11}],"city":[{"province":"上海","name":"上海","value":30},{"province":"北京","name":"北京","value":25},{"province":"广东","name":"广州","value":25},{"province":"浙江","name":"杭州","value":24},{"province":"江苏","name":"苏州","value":24},{"province":"湖北","name":"武汉","value":23},{"province":"四川","name":"成都","value":21},{"province":"陕西","name":"西安","value":16},{"province":"湖南","name":"长沙","value":16},{"province":"广东","name":"深圳","value":15},{"province":"福建","name":"厦门","value":14},{"province":"浙江","name":"台州","value":14},{"province":"重庆","name":"重庆","value":13},{"province":"浙江","name":"金华","value":12},{"province":"浙江","name":"温州","value":12},{"province":"江苏","name":"常州","value":11},{"province":"浙江","name":"嘉兴","value":11},{"province":"江苏","name":"南京","value":11},{"province":"江苏","name":"无锡","value":11},{"province":"吉林","name":"长春","value":11}]},"2022-12":{"total":265,"province":[{"name":"广东","value":53},{"name":"江苏","value":50},{"name":"浙江","value":47},{"name":"上海","value":29},{"name":"北京","value":19},{"name":"安徽","value":16},{"name":"四川","value":14},{"name":"福建","value":13},{"name":"湖南","value":13},{"name":"湖北","value":11}],"city":[{"province":"上海","name":"上海","value":29},{"province":"江苏","name":"苏州","value":22},{"province":"广东","name":"东莞","value":21},{"province":"北京","name":"北京","value":19},{"province":"广东","name":"深圳","value":18},{"province":"安徽","name":"合肥","value":16},{"province":"江苏","name":"南京","value":15},{"province":"四川","name":"成都","value":14},{"province":"广东","name":"广州","value":14},{"province":"福建","name":"厦门","value":13},{"province":"江苏","name":"无锡","value":13},{"province":"湖南","name":"长沙","value":13},{"province":"浙江","name":"金华","value":12},{"province":"浙江","name":"宁波","value":12},{"province":"浙江","name":"温州","value":12},{"province":"浙江","name":"杭州","value":11},{"province":"湖北","name":"武汉","value":11}]},"2022-11":{"total":185,"province":[{"name":"江苏","value":47},{"name":"上海","value":38},{"name":"广东","value":34},{"name":"浙江","value":30},{"name":"福建","value":13},{"name":"北京","value":12},{"name":"广西","value":11}],"city":[{"province":"上海","name":"上海","value":38},{"province":"广东","name":"深圳","value":21},{"province":"江苏","name":"苏州","value":21},{"province":"浙江","name":"杭州","value":18},{"province":"江苏","name":"无锡","value":14},{"province":"广东","name":"东莞","value":13},{"province":"福建","name":"厦门","value":13},{"province":"北京","name":"北京","value":12},{"province":"江苏","name":"南京","value":12},{"province":"浙江","name":"宁波","value":12},{"province":"广西","name":"南宁","value":11}]},"2022-10":{"total":173,"province":[{"name":"广东","value":53},{"name":"上海","value":26},{"name":"北京","value":18},{"name":"浙江","value":18},{"name":"江苏","value":17},{"name":"湖南","value":15},{"name":"重庆","value":13},{"name":"四川","value":13}],"city":[{"province":"上海","name":"上海","value":26},{"province":"北京","name":"北京","value":18},{"province":"浙江","name":"杭州","value":18},{"province":"广东","name":"深圳","value":18},{"province":"江苏","name":"苏州","value":17},{"province":"湖南","name":"长沙","value":15},{"province":"四川","name":"成都","value":13},{"province":"重庆","name":"重庆","value":13},{"province":"广东","name":"广州","value":13},{"province":"广东","name":"东莞","value":11},{"province":"广东","name":"佛山","value":11}]},"2022-09":{"total":202,"province":[{"name":"上海","value":47},{"name":"广东","value":43},{"name":"江苏","value":38},{"name":"浙江","value":32},{"name":"北京","value":30},{"name":"重庆","value":12}],"city":[{"province":"上海","name":"上海","value":47},{"province":"北京","name":"北京","value":30},{"province":"广东","name":"深圳","value":24},{"province":"浙江","name":"杭州","value":20},{"province":"江苏","name":"苏州","value":20},{"province":"广东","name":"广州","value":19},{"province":"江苏","name":"南京","value":18},{"province":"重庆","name":"重庆","value":12},{"province":"浙江","name":"金华","value":12}]},"2022-08":{"total":265,"province":[{"name":"广东","value":44},{"name":"上海","value":39},{"name":"北京","value":33},{"name":"浙江","value":30},{"name":"江苏","value":22},{"name":"湖北","value":21},{"name":"湖南","value":14},{"name":"四川","value":14},{"name":"陕西","value":13},{"name":"安徽","value":12},{"name":"云南","value":12},{"name":"重庆","value":11}],"city":[{"province":"上海","name":"上海","value":39},{"province":"北京","name":"北京","value":33},{"province":"广东","name":"深圳","value":23},{"province":"江苏","name":"苏州","value":22},{"province":"广东","name":"广州","value":21},{"province":"湖北","name":"武汉","value":21},{"province":"浙江","name":"杭州","value":18},{"province":"四川","name":"成都","value":14},{"province":"湖南","name":"长沙","value":14},{"province":"陕西","name":"西安","value":13},{"province":"安徽","name":"合肥","value":12},{"province":"云南","name":"昆明","value":12},{"province":"浙江","name":"温州","value":12},{"province":"重庆","name":"重庆","value":11}]},"2022-07":{"total":236,"province":[{"name":"上海","value":42},{"name":"江苏","value":31},{"name":"北京","value":25},{"name":"广东","value":25},{"name":"重庆","value":15},{"name":"湖南","value":14},{"name":"安徽","value":13},{"name":"四川","value":13},{"name":"浙江","value":13},{"name":"云南","value":12},{"name":"湖北","value":11},{"name":"山东","value":11},{"name":"陕西","value":11}],"city":[{"province":"上海","name":"上海","value":42},{"province":"北京","name":"北京","value":25},{"province":"江苏","name":"南京","value":17},{"province":"重庆","name":"重庆","value":15},{"province":"江苏","name":"苏州","value":14},{"province":"湖南","name":"长沙","value":14},{"province":"四川","name":"成都","value":13},{"province":"广东","name":"广州","value":13},{"province":"浙江","name":"杭州","value":13},{"province":"安徽","name":"合肥","value":13},{"province":"云南","name":"昆明","value":12},{"province":"广东","name":"深圳","value":12},{"province":"山东","name":"青岛","value":11},{"province":"湖北","name":"武汉","value":11},{"province":"陕西","name":"西安","value":11}]},"2022-06":{"total":346,"province":[{"name":"广东","value":80},{"name":"浙江","value":78},{"name":"江苏","value":58},{"name":"上海","value":24},{"name":"北京","value":21},{"name":"湖南","value":15},{"name":"安徽","value":14},{"name":"江西","value":12},{"name":"重庆","value":11},{"name":"湖北","value":11},{"name":"陕西","value":11},{"name":"四川","value":11}],"city":[{"province":"广东","name":"深圳","value":36},{"province":"浙江","name":"宁波","value":28},{"province":"上海","name":"上海","value":24},{"province":"浙江","name":"杭州","value":22},{"province":"北京","name":"北京","value":21},{"province":"江苏","name":"南京","value":21},{"province":"江苏","name":"苏州","value":21},{"province":"广东","name":"东莞","value":19},{"province":"江苏","name":"无锡","value":16},{"province":"浙江","name":"金华","value":15},{"province":"湖南","name":"长沙","value":15},{"province":"安徽","name":"合肥","value":14},{"province":"广东","name":"广州","value":13},{"province":"浙江","name":"台州","value":13},{"province":"广东","name":"佛山","value":12},{"province":"江西","name":"南昌","value":12},{"province":"四川","name":"成都","value":11},{"province":"重庆","name":"重庆","value":11},{"province":"湖北","name":"武汉","value":11},{"province":"陕西","name":"西安","value":11}]}}