{"2025-12":{"total":34,"province":[{"name":"重庆","value":21},{"name":"广东","value":13}],"city":[{"province":"重庆","name":"重庆","value":21},{"province":"广东","name":"惠州","value":13}]},"2025-11":{"total":105,"province":[{"name":"北京","value":21},{"name":"重庆","value":20},{"name":"陕西","value":16},{"name":"吉林","value":13},{"name":"四川","value":13},{"name":"江苏","value":11},{"name":"天津","value":11}],"city":[{"province":"北京","name":"北京","value":21},{"province":"重庆","name":"重庆","value":20},{"province":"陕西","name":"西安","value":16},{"province":"四川","name":"成都","value":13},{"province":"吉林","name":"长春","value":13},{"province":"江苏","name":"苏州","value":11},{"province":"天津","name":"天津","value":11}]},"2025-10":{"total":518,"province":[{"name":"广东","value":70},{"name":"上海","value":55},{"name":"山东","value":54},{"name":"北京","value":51},{"name":"四川","value":45},{"name":"江苏","value":31},{"name":"浙江","value":31},{"name":"安徽","value":26},{"name":"河南","value":21},{"name":"湖北","value":21},{"name":"吉林","value":21},{"name":"湖南","value":20},{"name":"天津","value":17},{"name":"陕西","value":16},{"name":"广西","value":14},{"name":"云南","value":14},{"name":"山西","value":11}],"city":[{"province":"上海","name":"上海","value":55},{"province":"北京","name":"北京","value":51},{"province":"四川","name":"成都","value":45},{"province":"广东","name":"深圳","value":32},{"province":"山东","name":"青岛","value":31},{"province":"江苏","name":"苏州","value":31},{"province":"安徽","name":"合肥","value":26},{"province":"广东","name":"广州","value":23},{"province":"山东","name":"济南","value":23},{"province":"湖北","name":"武汉","value":21},{"province":"吉林","name":"长春","value":21},{"province":"河南","name":"郑州","value":21},{"province":"湖南","name":"长沙","value":20},{"province":"浙江","name":"杭州","value":19},{"province":"天津","name":"天津","value":17},{"province":"陕西","name":"西安","value":16},{"province":"广东","name":"东莞","value":15},{"province":"云南","name":"昆明","value":14},{"province":"广西","name":"南宁","value":14},{"province":"浙江","name":"温州","value":12},{"province":"山西","name":"太原","value":11}]},"2025-09":{"total":890,"province":[{"name":"广东","value":115},{"name":"北京","value":103},{"name":"山东","value":76},{"name":"四川","value":64},{"name":"浙江","value":53},{"name":"吉林","value":48},{"name":"河南","value":47},{"name":"江苏","value":44},{"name":"河北","value":39},{"name":"上海","value":34},{"name":"天津","value":32},{"name":"安徽","value":25},{"name":"山西","value":24},{"name":"内蒙古","value":23},{"name":"湖南","value":20},{"name":"陕西","value":20},{"name":"新疆","value":18},{"name":"宁夏","value":17},{"name":"重庆","value":15},{"name":"广西","value":15},{"name":"甘肃","value":12},{"name":"湖北","value":12},{"name":"辽宁","value":12},{"name":"福建","value":11},{"name":"黑龙江","value":11}],"city":[{"province":"北京","name":"北京","value":103},{"province":"四川","name":"成都","value":64},{"province":"吉林","name":"长春","value":48},{"province":"河南","name":"郑州","value":47},{"province":"广东","name":"广州","value":38},{"province":"广东","name":"深圳","value":38},{"province":"上海","name":"上海","value":34},{"province":"山东","name":"青岛","value":33},{"province":"天津","name":"天津","value":32},{"province":"山东","name":"济南","value":31},{"province":"广东","name":"东莞","value":28},{"province":"安徽","name":"合肥","value":25},{"province":"山西","name":"太原","value":24},{"province":"内蒙古","name":"呼和浩特","value":23},{"province":"浙江","name":"宁波","value":22},{"province":"江苏","name":"苏州","value":22},{"province":"河北","name":"唐山","value":20},{"province":"陕西","name":"西安","value":20},{"province":"湖南","name":"长沙","value":20},{"province":"浙江","name":"杭州","value":19},{"province":"河北","name":"石家庄","value":19},{"province":"新疆","name":"乌鲁木齐","value":18},{"province":"宁夏","name":"银川","value":17},{"province":"重庆","name":"重庆","value":15},{"province":"广西","name":"南宁","value":15},{"province":"辽宁","name":"大连","value":12},{"province":"甘肃","name":"兰州","value":12},{"province":"山东","name":"临沂","value":12},{"province":"浙江","name":"温州","value":12},{"province":"湖北","name":"武汉","value":12},{"province":"江苏","name":"常州","value":11},{"province":"广东","name":"佛山","value":11},{"province":"黑龙江","name":"哈尔滨","value":11},{"province":"江苏","name":"南京","value":11},{"province":"福建","name":"厦门","value":11}]},"2025-08":{"total":730,"province":[{"name":"广东","value":97},{"name":"山东","value":72},{"name":"河南","value":69},{"name":"北京","value":54},{"name":"上海","value":54},{"name":"四川","value":51},{"name":"浙江","value":47},{"name":"河北","value":33},{"name":"江苏","value":29},{"name":"安徽","value":28},{"name":"湖南","value":28},{"name":"陕西","value":23},{"name":"天津","value":23},{"name":"吉林","value":22},{"name":"重庆","value":18},{"name":"黑龙江","value":18},{"name":"山西","value":17},{"name":"辽宁","value":14},{"name":"甘肃","value":11},{"name":"宁夏","value":11},{"name":"云南","value":11}],"city":[{"province":"河南","name":"郑州","value":56},{"province":"北京","name":"北京","value":54},{"province":"上海","name":"上海","value":54},{"province":"四川","name":"成都","value":51},{"province":"广东","name":"广州","value":32},{"province":"江苏","name":"苏州","value":29},{"province":"安徽","name":"合肥","value":28},{"province":"广东","name":"深圳","value":28},{"province":"湖南","name":"长沙","value":28},{"province":"山东","name":"青岛","value":26},{"province":"广东","name":"东莞","value":23},{"province":"山东","name":"济南","value":23},{"province":"天津","name":"天津","value":23},{"province":"陕西","name":"西安","value":23},{"province":"吉林","name":"长春","value":22},{"province":"重庆","name":"重庆","value":18},{"province":"黑龙江","name":"哈尔滨","value":18},{"province":"河北","name":"石家庄","value":18},{"province":"浙江","name":"温州","value":18},{"province":"山西","name":"太原","value":17},{"province":"浙江","name":"杭州","value":15},{"province":"河北","name":"唐山","value":15},{"province":"广东","name":"佛山","value":14},{"province":"浙江","name":"宁波","value":14},{"province":"辽宁","name":"沈阳","value":14},{"province":"河南","name":"洛阳","value":13},{"province":"山东","name":"烟台","value":12},{"province":"云南","name":"昆明","value":11},{"province":"甘肃","name":"兰州","value":11},{"province":"宁夏","name":"银川","value":11},{"province":"山东","name":"淄博","value":11}]},"2025-07":{"total":705,"province":[{"name":"广东","value":104},{"name":"北京","value":73},{"name":"山东","value":58},{"name":"浙江","value":47},{"name":"河南","value":40},{"name":"江苏","value":37},{"name":"吉林","value":33},{"name":"上海","value":32},{"name":"辽宁","value":31},{"name":"陕西","value":25},{"name":"河北","value":24},{"name":"四川","value":24},{"name":"重庆","value":21},{"name":"山西","value":19},{"name":"天津","value":18},{"name":"广西","value":17},{"name":"江西","value":17},{"name":"湖北","value":15},{"name":"湖南","value":15},{"name":"安徽","value":14},{"name":"黑龙江","value":14},{"name":"宁夏","value":14},{"name":"云南","value":13}],"city":[{"province":"北京","name":"北京","value":73},{"province":"河南","name":"郑州","value":40},{"province":"广东","name":"广州","value":38},{"province":"吉林","name":"长春","value":33},{"province":"山东","name":"济南","value":32},{"province":"上海","name":"上海","value":32},{"province":"广东","name":"深圳","value":30},{"province":"山东","name":"青岛","value":26},{"province":"陕西","name":"西安","value":25},{"province":"四川","name":"成都","value":24},{"province":"重庆","name":"重庆","value":21},{"province":"江苏","name":"苏州","value":20},{"province":"广东","name":"东莞","value":19},{"province":"山西","name":"太原","value":19},{"province":"辽宁","name":"沈阳","value":18},{"province":"天津","name":"天津","value":18},{"province":"广东","name":"佛山","value":17},{"province":"江西","name":"南昌","value":17},{"province":"江苏","name":"南京","value":17},{"province":"广西","name":"南宁","value":17},{"province":"湖北","name":"武汉","value":15},{"province":"湖南","name":"长沙","value":15},{"province":"黑龙江","name":"哈尔滨","value":14},{"province":"安徽","name":"合肥","value":14},{"province":"浙江","name":"金华","value":14},{"province":"宁夏","name":"银川","value":14},{"province":"辽宁","name":"大连","value":13},{"province":"云南","name":"昆明","value":13},{"province":"河北","name":"唐山","value":13},{"province":"浙江","name":"杭州","value":11},{"province":"浙江","name":"宁波","value":11},{"province":"河北","name":"石家庄","value":11},{"province":"浙江","name":"温州","value":11}]},"2025-06":{"total":638,"province":[{"name":"广东","value":80},{"name":"山东","value":72},{"name":"江苏","value":54},{"name":"浙江","value":46},{"name":"辽宁","value":45},{"name":"北京","value":32},{"name":"河南","value":32},{"name":"吉林","value":31},{"name":"四川","value":28},{"name":"上海","value":27},{"name":"陕西","value":20},{"name":"河北","value":18},{"name":"黑龙江","value":17},{"name":"重庆","value":16},{"name":"内蒙古","value":16},{"name":"山西","value":16},{"name":"湖北","value":14},{"name":"天津","value":14},{"name":"安徽","value":13},{"name":"广西","value":13},{"name":"江西","value":12},{"name":"福建","value":11},{"name":"湖南","value":11}],"city":[{"province":"山东","name":"青岛","value":36},{"province":"广东","name":"深圳","value":35},{"province":"北京","name":"北京","value":32},{"province":"广东","name":"广州","value":32},{"province":"河南","name":"郑州","value":32},{"province":"吉林","name":"长春","value":31},{"province":"辽宁","name":"沈阳","value":29},{"province":"四川","name":"成都","value":28},{"province":"上海","name":"上海","value":27},{"province":"山东","name":"济南","value":25},{"province":"江苏","name":"苏州","value":24},{"province":"陕西","name":"西安","value":20},{"province":"浙江","name":"杭州","value":19},{"province":"河北","name":"石家庄","value":18},{"province":"黑龙江","name":"哈尔滨","value":17},{"province":"重庆","name":"重庆","value":16},{"province":"辽宁","name":"大连","value":16},{"province":"内蒙古","name":"呼和浩特","value":16},{"province":"浙江","name":"金华","value":16},{"province":"山西","name":"太原","value":16},{"province":"江苏","name":"南京","value":15},{"province":"江苏","name":"徐州","value":15},{"province":"天津","name":"天津","value":14},{"province":"湖北","name":"武汉","value":14},{"province":"广东","name":"东莞","value":13},{"province":"安徽","name":"合肥","value":13},{"province":"广西","name":"南宁","value":13},{"province":"江西","name":"南昌","value":12},{"province":"福建","name":"厦门","value":11},{"province":"浙江","name":"台州","value":11},{"province":"山东","name":"潍坊","value":11},{"province":"湖南","name":"长沙","value":11}]},"2025-05":{"total":245,"province":[{"name":"四川","value":28},{"name":"江苏","value":27},{"name":"山东","value":26},{"name":"河南","value":24},{"name":"北京","value":22},{"name":"重庆","value":22},{"name":"广东","value":21},{"name":"安徽","value":14},{"name":"上海","value":14},{"name":"湖南","value":13},{"name":"浙江","value":12},{"name":"陕西","value":11},{"name":"天津","value":11}],"city":[{"province":"四川","name":"成都","value":28},{"province":"河南","name":"郑州","value":24},{"province":"北京","name":"北京","value":22},{"province":"重庆","name":"重庆","value":22},{"province":"广东","name":"深圳","value":21},{"province":"江苏","name":"苏州","value":15},{"province":"安徽","name":"合肥","value":14},{"province":"山东","name":"青岛","value":14},{"province":"上海","name":"上海","value":14},{"province":"湖南","name":"长沙","value":13},{"province":"浙江","name":"杭州","value":12},{"province":"山东","name":"济南","value":12},{"province":"江苏","name":"南京","value":12},{"province":"天津","name":"天津","value":11},{"province":"陕西","name":"西安","value":11}]},"2025-04":{"total":134,"province":[{"name":"广东","value":34},{"name":"四川","value":28},{"name":"北京","value":21},{"name":"河南","value":16},{"name":"安徽","value":13},{"name":"上海","value":11},{"name":"浙江","value":11}],"city":[{"province":"四川","name":"成都","value":28},{"province":"广东","name":"深圳","value":23},{"province":"北京","name":"北京","value":21},{"province":"河南","name":"郑州","value":16},{"province":"安徽","name":"合肥","value":13},{"province":"广东","name":"东莞","value":11},{"province":"浙江","name":"杭州","value":11},{"province":"上海","name":"上海","value":11}]},"2025-03":{"total":86,"province":[{"name":"上海","value":25},{"name":"江苏","value":20},{"name":"广东","value":15},{"name":"四川","value":14},{"name":"北京","value":12}],"city":[{"province":"上海","name":"上海","value":25},{"province":"江苏","name":"苏州","value":20},{"province":"广东","name":"广州","value":15},{"province":"四川","name":"成都","value":14},{"province":"北京","name":"北京","value":12}]},"2025-02":{"total":11,"province":[{"name":"四川","value":11}],"city":[{"province":"四川","name":"成都","value":11}]},"2025-01":{"total":103,"province":[{"name":"河南","value":17},{"name":"重庆","value":16},{"name":"四川","value":16},{"name":"广东","value":15},{"name":"湖南","value":15},{"name":"北京","value":13},{"name":"江苏","value":11}],"city":[{"province":"河南","name":"郑州","value":17},{"province":"四川","name":"成都","value":16},{"province":"重庆","name":"重庆","value":16},{"province":"广东","name":"东莞","value":15},{"province":"湖南","name":"长沙","value":15},{"province":"北京","name":"北京","value":13},{"province":"江苏","name":"苏州","value":11}]},"2024-12":{"total":351,"province":[{"name":"江苏","value":39},{"name":"山东","value":39},{"name":"北京","value":34},{"name":"广东","value":32},{"name":"上海","value":28},{"name":"浙江","value":25},{"name":"四川","value":24},{"name":"河南","value":20},{"name":"安徽","value":17},{"name":"湖北","value":16},{"name":"重庆","value":15},{"name":"陕西","value":14},{"name":"湖南","value":13},{"name":"广西","value":12},{"name":"河北","value":12},{"name":"贵州","value":11}],"city":[{"province":"北京","name":"北京","value":34},{"province":"上海","name":"上海","value":28},{"province":"四川","name":"成都","value":24},{"province":"山东","name":"济南","value":21},{"province":"广东","name":"深圳","value":21},{"province":"河南","name":"郑州","value":20},{"province":"山东","name":"青岛","value":18},{"province":"安徽","name":"合肥","value":17},{"province":"湖北","name":"武汉","value":16},{"province":"重庆","name":"重庆","value":15},{"province":"浙江","name":"温州","value":14},{"province":"陕西","name":"西安","value":14},{"province":"江苏","name":"常州","value":13},{"province":"江苏","name":"南京","value":13},{"province":"江苏","name":"苏州","value":13},{"province":"湖南","name":"长沙","value":13},{"province":"广西","name":"南宁","value":12},{"province":"河北","name":"唐山","value":12},{"province":"广东","name":"广州","value":11},{"province":"贵州","name":"贵阳","value":11},{"province":"浙江","name":"金华","value":11}]},"2024-11":{"total":412,"province":[{"name":"浙江","value":68},{"name":"广东","value":54},{"name":"江苏","value":50},{"name":"上海","value":35},{"name":"北京","value":34},{"name":"山东","value":34},{"name":"四川","value":33},{"name":"安徽","value":26},{"name":"重庆","value":24},{"name":"陕西","value":17},{"name":"吉林","value":13},{"name":"湖北","value":12},{"name":"湖南","value":12}],"city":[{"province":"上海","name":"上海","value":35},{"province":"北京","name":"北京","value":34},{"province":"四川","name":"成都","value":33},{"province":"江苏","name":"苏州","value":28},{"province":"安徽","name":"合肥","value":26},{"province":"重庆","name":"重庆","value":24},{"province":"江苏","name":"南京","value":22},{"province":"广东","name":"深圳","value":21},{"province":"广东","name":"广州","value":19},{"province":"浙江","name":"金华","value":19},{"province":"山东","name":"青岛","value":18},{"province":"浙江","name":"杭州","value":17},{"province":"陕西","name":"西安","value":17},{"province":"山东","name":"济南","value":16},{"province":"浙江","name":"宁波","value":16},{"province":"浙江","name":"温州","value":16},{"province":"广东","name":"东莞","value":14},{"province":"吉林","name":"长春","value":13},{"province":"湖北","name":"武汉","value":12},{"province":"湖南","name":"长沙","value":12}]},"2024-10":{"total":567,"province":[{"name":"江苏","value":79},{"name":"广东","value":65},{"name":"四川","value":55},{"name":"上海","value":53},{"name":"浙江","value":51},{"name":"北京","value":48},{"name":"重庆","value":28},{"name":"山东","value":26},{"name":"安徽","value":25},{"name":"河南","value":20},{"name":"陕西","value":18},{"name":"贵州","value":15},{"name":"湖南","value":14},{"name":"吉林","value":13},{"name":"江西","value":13},{"name":"辽宁","value":11},{"name":"内蒙古","value":11},{"name":"天津","value":11},{"name":"云南","value":11}],"city":[{"province":"四川","name":"成都","value":55},{"province":"上海","name":"上海","value":53},{"province":"北京","name":"北京","value":48},{"province":"江苏","name":"苏州","value":35},{"province":"江苏","name":"南京","value":31},{"province":"重庆","name":"重庆","value":28},{"province":"安徽","name":"合肥","value":25},{"province":"浙江","name":"宁波","value":22},{"province":"河南","name":"郑州","value":20},{"province":"广东","name":"广州","value":19},{"province":"广东","name":"深圳","value":18},{"province":"陕西","name":"西安","value":18},{"province":"浙江","name":"杭州","value":17},{"province":"广东","name":"东莞","value":15},{"province":"贵州","name":"贵阳","value":15},{"province":"山东","name":"青岛","value":15},{"province":"湖南","name":"长沙","value":14},{"province":"江苏","name":"常州","value":13},{"province":"广东","name":"佛山","value":13},{"province":"江西","name":"南昌","value":13},{"province":"吉林","name":"长春","value":13},{"province":"浙江","name":"温州","value":12},{"province":"内蒙古","name":"呼和浩特","value":11},{"province":"山东","name":"济南","value":11},{"province":"云南","name":"昆明","value":11},{"province":"辽宁","name":"沈阳","value":11},{"province":"天津","name":"天津","value":11}]},"2024-09":{"total":775,"province":[{"name":"江苏","value":110},{"name":"广东","value":98},{"name":"四川","value":86},{"name":"浙江","value":82},{"name":"安徽","value":50},{"name":"上海","value":49},{"name":"北京","value":48},{"name":"山东","value":39},{"name":"重庆","value":29},{"name":"河南","value":29},{"name":"陕西","value":26},{"name":"广西","value":21},{"name":"湖北","value":19},{"name":"天津","value":19},{"name":"吉林","value":15},{"name":"江西","value":15},{"name":"湖南","value":14},{"name":"河北","value":13},{"name":"黑龙江","value":13}],"city":[{"province":"四川","name":"成都","value":86},{"province":"上海","name":"上海","value":49},{"province":"北京","name":"北京","value":48},{"province":"江苏","name":"苏州","value":42},{"province":"广东","name":"深圳","value":40},{"province":"江苏","name":"南京","value":39},{"province":"安徽","name":"合肥","value":37},{"province":"重庆","name":"重庆","value":29},{"province":"河南","name":"郑州","value":29},{"province":"广东","name":"广州","value":28},{"province":"浙江","name":"金华","value":28},{"province":"陕西","name":"西安","value":26},{"province":"山东","name":"青岛","value":23},{"province":"浙江","name":"杭州","value":21},{"province":"广西","name":"南宁","value":21},{"province":"浙江","name":"宁波","value":20},{"province":"天津","name":"天津","value":19},{"province":"湖北","name":"武汉","value":19},{"province":"江苏","name":"常州","value":18},{"province":"广东","name":"东莞","value":17},{"province":"山东","name":"济南","value":16},{"province":"江西","name":"南昌","value":15},{"province":"吉林","name":"长春","value":15},{"province":"湖南","name":"长沙","value":14},{"province":"广东","name":"佛山","value":13},{"province":"安徽","name":"阜阳","value":13},{"province":"黑龙江","name":"哈尔滨","value":13},{"province":"河北","name":"石家庄","value":13},{"province":"浙江","name":"台州","value":13},{"province":"江苏","name":"无锡","value":11}]},"2024-08":{"total":505,"province":[{"name":"广东","value":59},{"name":"浙江","value":53},{"name":"江苏","value":52},{"name":"上海","value":50},{"name":"四川","value":49},{"name":"北京","value":46},{"name":"安徽","value":35},{"name":"山东","value":32},{"name":"重庆","value":22},{"name":"河南","value":22},{"name":"陕西","value":16},{"name":"河北","value":15},{"name":"湖北","value":14},{"name":"辽宁","value":14},{"name":"湖南","value":13},{"name":"天津","value":13}],"city":[{"province":"上海","name":"上海","value":50},{"province":"四川","name":"成都","value":49},{"province":"北京","name":"北京","value":46},{"province":"安徽","name":"合肥","value":35},{"province":"江苏","name":"苏州","value":27},{"province":"广东","name":"广州","value":25},{"province":"浙江","name":"杭州","value":25},{"province":"江苏","name":"南京","value":25},{"province":"重庆","name":"重庆","value":22},{"province":"河南","name":"郑州","value":22},{"province":"山东","name":"青岛","value":21},{"province":"广东","name":"深圳","value":21},{"province":"浙江","name":"金华","value":17},{"province":"陕西","name":"西安","value":16},{"province":"河北","name":"石家庄","value":15},{"province":"辽宁","name":"沈阳","value":14},{"province":"湖北","name":"武汉","value":14},{"province":"广东","name":"东莞","value":13},{"province":"天津","name":"天津","value":13},{"province":"湖南","name":"长沙","value":13},{"province":"山东","name":"济南","value":11},{"province":"浙江","name":"温州","value":11}]},"2024-07":{"total":554,"province":[{"name":"广东","value":88},{"name":"浙江","value":68},{"name":"江苏","value":48},{"name":"北京","value":37},{"name":"四川","value":36},{"name":"上海","value":35},{"name":"山东","value":31},{"name":"安徽","value":27},{"name":"河南","value":27},{"name":"天津","value":24},{"name":"湖南","value":23},{"name":"重庆","value":21},{"name":"湖北","value":17},{"name":"陕西","value":17},{"name":"辽宁","value":16},{"name":"吉林","value":15},{"name":"贵州","value":12},{"name":"江西","value":12}],"city":[{"province":"北京","name":"北京","value":37},{"province":"四川","name":"成都","value":36},{"province":"上海","name":"上海","value":35},{"province":"浙江","name":"宁波","value":34},{"province":"广东","name":"广州","value":33},{"province":"江苏","name":"苏州","value":32},{"province":"安徽","name":"合肥","value":27},{"province":"广东","name":"深圳","value":27},{"province":"河南","name":"郑州","value":27},{"province":"天津","name":"天津","value":24},{"province":"浙江","name":"杭州","value":23},{"province":"湖南","name":"长沙","value":23},{"province":"重庆","name":"重庆","value":21},{"province":"广东","name":"东莞","value":17},{"province":"山东","name":"青岛","value":17},{"province":"湖北","name":"武汉","value":17},{"province":"陕西","name":"西安","value":17},{"province":"江苏","name":"南京","value":16},{"province":"辽宁","name":"沈阳","value":16},{"province":"吉林","name":"长春","value":15},{"province":"山东","name":"济南","value":14},{"province":"贵州","name":"贵阳","value":12},{"province":"江西","name":"南昌","value":12},{"province":"广东","name":"佛山","value":11},{"province":"浙江","name":"绍兴","value":11}]},"2024-06":{"total":417,"province":[{"name":"浙江","value":71},{"name":"广东","value":62},{"name":"江苏","value":50},{"name":"上海","value":42},{"name":"北京","value":38},{"name":"山东","value":26},{"name":"河南","value":20},{"name":"四川","value":20},{"name":"安徽","value":19},{"name":"天津","value":17},{"name":"重庆","value":16},{"name":"辽宁","value":14},{"name":"湖北","value":11},{"name":"湖南","value":11}],"city":[{"province":"上海","name":"上海","value":42},{"province":"北京","name":"北京","value":38},{"province":"江苏","name":"苏州","value":33},{"province":"浙江","name":"宁波","value":23},{"province":"浙江","name":"杭州","value":21},{"province":"广东","name":"深圳","value":21},{"province":"四川","name":"成都","value":20},{"province":"河南","name":"郑州","value":20},{"province":"安徽","name":"合肥","value":19},{"province":"江苏","name":"南京","value":17},{"province":"天津","name":"天津","value":17},{"province":"重庆","name":"重庆","value":16},{"province":"广东","name":"广州","value":16},{"province":"浙江","name":"金华","value":15},{"province":"山东","name":"青岛","value":15},{"province":"广东","name":"佛山","value":14},{"province":"辽宁","name":"沈阳","value":14},{"province":"浙江","name":"绍兴","value":12},{"province":"广东","name":"东莞","value":11},{"province":"山东","name":"济南","value":11},{"province":"湖北","name":"武汉","value":11},{"province":"湖南","name":"长沙","value":11}]},"2024-05":{"total":382,"province":[{"name":"广东","value":59},{"name":"江苏","value":53},{"name":"浙江","value":47},{"name":"四川","value":36},{"name":"上海","value":29},{"name":"北京","value":26},{"name":"山东","value":23},{"name":"河南","value":22},{"name":"安徽","value":18},{"name":"湖北","value":18},{"name":"湖南","value":16},{"name":"重庆","value":13},{"name":"黑龙江","value":11},{"name":"天津","value":11}],"city":[{"province":"四川","name":"成都","value":36},{"province":"江苏","name":"苏州","value":34},{"province":"上海","name":"上海","value":29},{"province":"北京","name":"北京","value":26},{"province":"浙江","name":"杭州","value":24},{"province":"浙江","name":"宁波","value":23},{"province":"山东","name":"青岛","value":23},{"province":"河南","name":"郑州","value":22},{"province":"广东","name":"深圳","value":21},{"province":"江苏","name":"南京","value":19},{"province":"安徽","name":"合肥","value":18},{"province":"湖北","name":"武汉","value":18},{"province":"湖南","name":"长沙","value":16},{"province":"广东","name":"东莞","value":14},{"province":"重庆","name":"重庆","value":13},{"province":"广东","name":"佛山","value":12},{"province":"广东","name":"广州","value":12},{"province":"黑龙江","name":"哈尔滨","value":11},{"province":"天津","name":"天津","value":11}]},"2024-04":{"total":335,"province":[{"name":"广东","value":50},{"name":"上海","value":45},{"name":"浙江","value":44},{"name":"四川","value":39},{"name":"江苏","value":36},{"name":"北京","value":24},{"name":"河南","value":15},{"name":"陕西","value":15},{"name":"安徽","value":14},{"name":"重庆","value":14},{"name":"湖南","value":14},{"name":"天津","value":13},{"name":"湖北","value":12}],"city":[{"province":"上海","name":"上海","value":45},{"province":"四川","name":"成都","value":39},{"province":"浙江","name":"杭州","value":31},{"province":"北京","name":"北京","value":24},{"province":"广东","name":"深圳","value":21},{"province":"江苏","name":"苏州","value":19},{"province":"江苏","name":"南京","value":17},{"province":"广东","name":"东莞","value":15},{"province":"陕西","name":"西安","value":15},{"province":"河南","name":"郑州","value":15},{"province":"重庆","name":"重庆","value":14},{"province":"广东","name":"广州","value":14},{"province":"安徽","name":"合肥","value":14},{"province":"湖南","name":"长沙","value":14},{"province":"浙江","name":"宁波","value":13},{"province":"天津","name":"天津","value":13},{"province":"湖北","name":"武汉","value":12}]},"2024-03":{"total":279,"province":[{"name":"浙江","value":58},{"name":"江苏","value":43},{"name":"上海","value":38},{"name":"四川","value":28},{"name":"北京","value":26},{"name":"安徽","value":17},{"name":"湖南","value":17},{"name":"重庆","value":15},{"name":"陕西","value":14},{"name":"广东","value":12},{"name":"河南","value":11}],"city":[{"province":"上海","name":"上海","value":38},{"province":"浙江","name":"杭州","value":37},{"province":"江苏","name":"苏州","value":29},{"province":"四川","name":"成都","value":28},{"province":"北京","name":"北京","value":26},{"province":"浙江","name":"宁波","value":21},{"province":"安徽","name":"合肥","value":17},{"province":"湖南","name":"长沙","value":17},{"province":"重庆","name":"重庆","value":15},{"province":"江苏","name":"南京","value":14},{"province":"陕西","name":"西安","value":14},{"province":"广东","name":"广州","value":12},{"province":"河南","name":"郑州","value":11}]},"2024-02":{"total":142,"province":[{"name":"四川","value":31},{"name":"安徽","value":21},{"name":"上海","value":20},{"name":"北京","value":17},{"name":"重庆","value":17},{"name":"江苏","value":14},{"name":"广东","value":11},{"name":"浙江","value":11}],"city":[{"province":"四川","name":"成都","value":31},{"province":"安徽","name":"合肥","value":21},{"province":"上海","name":"上海","value":20},{"province":"北京","name":"北京","value":17},{"province":"重庆","name":"重庆","value":17},{"province":"江苏","name":"南京","value":14},{"province":"浙江","name":"杭州","value":11},{"province":"广东","name":"深圳","value":11}]},"2024-01":{"total":423,"province":[{"name":"广东","value":84},{"name":"浙江","value":74},{"name":"上海","value":38},{"name":"北京","value":36},{"name":"四川","value":35},{"name":"江苏","value":26},{"name":"湖北","value":20},{"name":"陕西","value":18},{"name":"重庆","value":17},{"name":"广西","value":16},{"name":"湖南","value":16},{"name":"安徽","value":15},{"name":"天津","value":15},{"name":"山东","value":13}],"city":[{"province":"上海","name":"上海","value":38},{"province":"北京","name":"北京","value":36},{"province":"四川","name":"成都","value":35},{"province":"浙江","name":"杭州","value":35},{"province":"广东","name":"广州","value":28},{"province":"广东","name":"深圳","value":27},{"province":"江苏","name":"苏州","value":26},{"province":"浙江","name":"宁波","value":25},{"province":"湖北","name":"武汉","value":20},{"province":"陕西","name":"西安","value":18},{"province":"重庆","name":"重庆","value":17},{"province":"广东","name":"东莞","value":16},{"province":"广西","name":"南宁","value":16},{"province":"湖南","name":"长沙","value":16},{"province":"安徽","name":"合肥","value":15},{"province":"天津","name":"天津","value":15},{"province":"浙江","name":"金华","value":14},{"province":"广东","name":"佛山","value":13},{"province":"山东","name":"青岛","value":13}]},"2023-12":{"total":488,"province":[{"name":"广东","value":62},{"name":"浙江","value":61},{"name":"江苏","value":59},{"name":"四川","value":59},{"name":"上海","value":53},{"name":"北京","value":42},{"name":"山东","value":27},{"name":"重庆","value":22},{"name":"湖南","value":20},{"name":"安徽","value":17},{"name":"陕西","value":17},{"name":"河南","value":14},{"name":"辽宁","value":13},{"name":"福建","value":11},{"name":"江西","value":11}],"city":[{"province":"四川","name":"成都","value":59},{"province":"上海","name":"上海","value":53},{"province":"北京","name":"北京","value":42},{"province":"江苏","name":"苏州","value":41},{"province":"浙江","name":"杭州","value":34},{"province":"重庆","name":"重庆","value":22},{"province":"广东","name":"深圳","value":20},{"province":"湖南","name":"长沙","value":20},{"province":"江苏","name":"南京","value":18},{"province":"安徽","name":"合肥","value":17},{"province":"陕西","name":"西安","value":17},{"province":"广东","name":"广州","value":15},{"province":"浙江","name":"宁波","value":15},{"province":"广东","name":"东莞","value":14},{"province":"山东","name":"济南","value":14},{"province":"河南","name":"郑州","value":14},{"province":"广东","name":"佛山","value":13},{"province":"山东","name":"青岛","value":13},{"province":"辽宁","name":"沈阳","value":13},{"province":"浙江","name":"温州","value":12},{"province":"江西","name":"南昌","value":11},{"province":"福建","name":"厦门","value":11}]},"2023-11":{"total":434,"province":[{"name":"广东","value":82},{"name":"浙江","value":65},{"name":"江苏","value":45},{"name":"北京","value":37},{"name":"四川","value":30},{"name":"上海","value":29},{"name":"湖北","value":21},{"name":"湖南","value":21},{"name":"重庆","value":20},{"name":"陕西","value":18},{"name":"安徽","value":17},{"name":"山东","value":13},{"name":"天津","value":13},{"name":"河南","value":12},{"name":"广西","value":11}],"city":[{"province":"北京","name":"北京","value":37},{"province":"四川","name":"成都","value":30},{"province":"上海","name":"上海","value":29},{"province":"江苏","name":"苏州","value":28},{"province":"浙江","name":"杭州","value":26},{"province":"广东","name":"深圳","value":24},{"province":"广东","name":"广州","value":21},{"province":"湖北","name":"武汉","value":21},{"province":"湖南","name":"长沙","value":21},{"province":"重庆","name":"重庆","value":20},{"province":"广东","name":"佛山","value":20},{"province":"陕西","name":"西安","value":18},{"province":"广东","name":"东莞","value":17},{"province":"安徽","name":"合肥","value":17},{"province":"江苏","name":"南京","value":17},{"province":"浙江","name":"宁波","value":14},{"province":"浙江","name":"金华","value":13},{"province":"山东","name":"青岛","value":13},{"province":"天津","name":"天津","value":13},{"province":"浙江","name":"嘉兴","value":12},{"province":"河南","name":"郑州","value":12},{"province":"广西","name":"南宁","value":11}]},"2023-10":{"total":352,"province":[{"name":"江苏","value":45},{"name":"广东","value":40},{"name":"上海","value":39},{"name":"浙江","value":32},{"name":"北京","value":29},{"name":"辽宁","value":28},{"name":"四川","value":27},{"name":"陕西","value":20},{"name":"湖南","value":17},{"name":"广西","value":15},{"name":"湖北","value":14},{"name":"安徽","value":12},{"name":"天津","value":12},{"name":"福建","value":11},{"name":"云南","value":11}],"city":[{"province":"上海","name":"上海","value":39},{"province":"北京","name":"北京","value":29},{"province":"四川","name":"成都","value":27},{"province":"广东","name":"深圳","value":26},{"province":"陕西","name":"西安","value":20},{"province":"浙江","name":"杭州","value":17},{"province":"湖南","name":"长沙","value":17},{"province":"广西","name":"南宁","value":15},{"province":"浙江","name":"宁波","value":15},{"province":"辽宁","name":"沈阳","value":15},{"province":"广东","name":"广州","value":14},{"province":"湖北","name":"武汉","value":14},{"province":"辽宁","name":"大连","value":13},{"province":"安徽","name":"合肥","value":12},{"province":"江苏","name":"南京","value":12},{"province":"天津","name":"天津","value":12},{"province":"云南","name":"昆明","value":11},{"province":"江苏","name":"南通","value":11},{"province":"福建","name":"泉州","value":11},{"province":"江苏","name":"苏州","value":11},{"province":"江苏","name":"无锡","value":11}]},"2023-09":{"total":859,"province":[{"name":"浙江","value":130},{"name":"江苏","value":120},{"name":"广东","value":102},{"name":"四川","value":79},{"name":"北京","value":64},{"name":"上海","value":61},{"name":"山东","value":42},{"name":"重庆","value":37},{"name":"辽宁","value":32},{"name":"湖南","value":30},{"name":"陕西","value":23},{"name":"安徽","value":21},{"name":"湖北","value":20},{"name":"天津","value":18},{"name":"河南","value":17},{"name":"广西","value":14},{"name":"河北","value":14},{"name":"黑龙江","value":12},{"name":"云南","value":12},{"name":"福建","value":11}],"city":[{"province":"四川","name":"成都","value":79},{"province":"北京","name":"北京","value":64},{"province":"上海","name":"上海","value":61},{"province":"江苏","name":"苏州","value":47},{"province":"重庆","name":"重庆","value":37},{"province":"浙江","name":"杭州","value":37},{"province":"江苏","name":"南京","value":35},{"province":"广东","name":"深圳","value":34},{"province":"湖南","name":"长沙","value":30},{"province":"浙江","name":"宁波","value":28},{"province":"山东","name":"青岛","value":26},{"province":"广东","name":"东莞","value":24},{"province":"广东","name":"广州","value":24},{"province":"陕西","name":"西安","value":23},{"province":"安徽","name":"合肥","value":21},{"province":"浙江","name":"嘉兴","value":21},{"province":"辽宁","name":"大连","value":20},{"province":"广东","name":"佛山","value":20},{"province":"湖北","name":"武汉","value":20},{"province":"浙江","name":"金华","value":19},{"province":"天津","name":"天津","value":18},{"province":"河南","name":"郑州","value":17},{"province":"山东","name":"济南","value":16},{"province":"广西","name":"南宁","value":14},{"province":"江苏","name":"南通","value":14},{"province":"浙江","name":"绍兴","value":14},{"province":"河北","name":"石家庄","value":14},{"province":"黑龙江","name":"哈尔滨","value":12},{"province":"云南","name":"昆明","value":12},{"province":"辽宁","name":"沈阳","value":12},{"province":"江苏","name":"无锡","value":12},{"province":"江苏","name":"徐州","value":12},{"province":"福建","name":"厦门","value":11},{"province":"浙江","name":"温州","value":11}]},"2023-08":{"total":812,"province":[{"name":"浙江","value":111},{"name":"江苏","value":103},{"name":"广东","value":92},{"name":"北京","value":72},{"name":"四川","value":71},{"name":"上海","value":56},{"name":"重庆","value":32},{"name":"山东","value":31},{"name":"福建","value":28},{"name":"陕西","value":25},{"name":"辽宁","value":23},{"name":"安徽","value":22},{"name":"湖北","value":22},{"name":"广西","value":18},{"name":"贵州","value":18},{"name":"湖南","value":18},{"name":"天津","value":18},{"name":"河北","value":15},{"name":"河南","value":13},{"name":"江西","value":13},{"name":"吉林","value":11}],"city":[{"province":"北京","name":"北京","value":72},{"province":"四川","name":"成都","value":71},{"province":"上海","name":"上海","value":56},{"province":"江苏","name":"苏州","value":42},{"province":"浙江","name":"杭州","value":41},{"province":"重庆","name":"重庆","value":32},{"province":"广东","name":"广州","value":25},{"province":"陕西","name":"西安","value":25},{"province":"广东","name":"东莞","value":24},{"province":"江苏","name":"南京","value":23},{"province":"辽宁","name":"沈阳","value":23},{"province":"安徽","name":"合肥","value":22},{"province":"广东","name":"深圳","value":22},{"province":"湖北","name":"武汉","value":22},{"province":"广东","name":"佛山","value":21},{"province":"浙江","name":"绍兴","value":20},{"province":"浙江","name":"宁波","value":19},{"province":"贵州","name":"贵阳","value":18},{"province":"山东","name":"济南","value":18},{"province":"广西","name":"南宁","value":18},{"province":"天津","name":"天津","value":18},{"province":"浙江","name":"温州","value":18},{"province":"湖南","name":"长沙","value":18},{"province":"江苏","name":"无锡","value":16},{"province":"福建","name":"厦门","value":15},{"province":"河北","name":"石家庄","value":15},{"province":"浙江","name":"嘉兴","value":13},{"province":"江西","name":"南昌","value":13},{"province":"山东","name":"青岛","value":13},{"province":"福建","name":"泉州","value":13},{"province":"河南","name":"郑州","value":13},{"province":"江苏","name":"南通","value":11},{"province":"江苏","name":"徐州","value":11},{"province":"吉林","name":"长春","value":11}]},"2023-07":{"total":762,"province":[{"name":"浙江","value":142},{"name":"广东","value":110},{"name":"江苏","value":88},{"name":"北京","value":54},{"name":"四川","value":48},{"name":"上海","value":44},{"name":"辽宁","value":39},{"name":"重庆","value":32},{"name":"陕西","value":31},{"name":"安徽","value":20},{"name":"福建","value":18},{"name":"广西","value":18},{"name":"河南","value":18},{"name":"湖南","value":17},{"name":"天津","value":17},{"name":"贵州","value":15},{"name":"山东","value":15},{"name":"云南","value":13},{"name":"山西","value":12},{"name":"湖北","value":11}],"city":[{"province":"北京","name":"北京","value":54},{"province":"四川","name":"成都","value":48},{"province":"江苏","name":"苏州","value":46},{"province":"上海","name":"上海","value":44},{"province":"广东","name":"广州","value":37},{"province":"浙江","name":"杭州","value":37},{"province":"广东","name":"深圳","value":35},{"province":"重庆","name":"重庆","value":32},{"province":"浙江","name":"宁波","value":31},{"province":"陕西","name":"西安","value":31},{"province":"浙江","name":"金华","value":28},{"province":"广东","name":"东莞","value":26},{"province":"江苏","name":"无锡","value":22},{"province":"辽宁","name":"大连","value":20},{"province":"安徽","name":"合肥","value":20},{"province":"江苏","name":"南京","value":20},{"province":"辽宁","name":"沈阳","value":19},{"province":"广西","name":"南宁","value":18},{"province":"福建","name":"厦门","value":18},{"province":"河南","name":"郑州","value":18},{"province":"天津","name":"天津","value":17},{"province":"浙江","name":"温州","value":17},{"province":"湖南","name":"长沙","value":17},{"province":"浙江","name":"绍兴","value":16},{"province":"贵州","name":"贵阳","value":15},{"province":"山东","name":"济南","value":15},{"province":"浙江","name":"嘉兴","value":13},{"province":"云南","name":"昆明","value":13},{"province":"广东","name":"佛山","value":12},{"province":"山西","name":"太原","value":12},{"province":"湖北","name":"武汉","value":11}]},"2023-06":{"total":750,"province":[{"name":"浙江","value":126},{"name":"江苏","value":109},{"name":"广东","value":83},{"name":"四川","value":54},{"name":"北京","value":53},{"name":"上海","value":49},{"name":"山东","value":44},{"name":"重庆","value":33},{"name":"福建","value":26},{"name":"辽宁","value":25},{"name":"湖南","value":24},{"name":"安徽","value":23},{"name":"陕西","value":22},{"name":"河南","value":21},{"name":"天津","value":18},{"name":"河北","value":15},{"name":"广西","value":14},{"name":"湖北","value":11}],"city":[{"province":"四川","name":"成都","value":54},{"province":"北京","name":"北京","value":53},{"province":"浙江","name":"杭州","value":51},{"province":"上海","name":"上海","value":49},{"province":"江苏","name":"苏州","value":45},{"province":"广东","name":"深圳","value":34},{"province":"重庆","name":"重庆","value":33},{"province":"广东","name":"广州","value":32},{"province":"浙江","name":"宁波","value":24},{"province":"山东","name":"青岛","value":24},{"province":"湖南","name":"长沙","value":24},{"province":"安徽","name":"合肥","value":23},{"province":"江苏","name":"南京","value":23},{"province":"陕西","name":"西安","value":22},{"province":"河南","name":"郑州","value":21},{"province":"山东","name":"济南","value":20},{"province":"浙江","name":"金华","value":20},{"province":"江苏","name":"南通","value":18},{"province":"天津","name":"天津","value":18},{"province":"广东","name":"东莞","value":17},{"province":"浙江","name":"温州","value":17},{"province":"福建","name":"厦门","value":15},{"province":"河北","name":"石家庄","value":15},{"province":"广西","name":"南宁","value":14},{"province":"浙江","name":"绍兴","value":14},{"province":"辽宁","name":"沈阳","value":14},{"province":"江苏","name":"徐州","value":12},{"province":"辽宁","name":"大连","value":11},{"province":"福建","name":"泉州","value":11},{"province":"江苏","name":"无锡","value":11},{"province":"湖北","name":"武汉","value":11}]},"2023-05":{"total":638,"province":[{"name":"广东","value":112},{"name":"江苏","value":97},{"name":"浙江","value":90},{"name":"上海","value":63},{"name":"四川","value":51},{"name":"山东","value":25},{"name":"湖南","value":23},{"name":"北京","value":20},{"name":"重庆","value":20},{"name":"陕西","value":19},{"name":"河南","value":18},{"name":"湖北","value":16},{"name":"安徽","value":15},{"name":"福建","value":15},{"name":"辽宁","value":15},{"name":"山西","value":14},{"name":"天津","value":14},{"name":"广西","value":11}],"city":[{"province":"上海","name":"上海","value":63},{"province":"四川","name":"成都","value":51},{"province":"江苏","name":"苏州","value":34},{"province":"浙江","name":"杭州","value":32},{"province":"广东","name":"深圳","value":32},{"province":"广东","name":"广州","value":26},{"province":"浙江","name":"宁波","value":25},{"province":"山东","name":"青岛","value":25},{"province":"广东","name":"佛山","value":24},{"province":"湖南","name":"长沙","value":23},{"province":"江苏","name":"南京","value":22},{"province":"浙江","name":"金华","value":21},{"province":"北京","name":"北京","value":20},{"province":"重庆","name":"重庆","value":20},{"province":"陕西","name":"西安","value":19},{"province":"河南","name":"郑州","value":18},{"province":"江苏","name":"常州","value":16},{"province":"广东","name":"东莞","value":16},{"province":"湖北","name":"武汉","value":16},{"province":"安徽","name":"合肥","value":15},{"province":"福建","name":"厦门","value":15},{"province":"辽宁","name":"沈阳","value":15},{"province":"山西","name":"太原","value":14},{"province":"天津","name":"天津","value":14},{"province":"江苏","name":"无锡","value":14},{"province":"广东","name":"中山","value":14},{"province":"浙江","name":"温州","value":12},{"province":"广西","name":"南宁","value":11},{"province":"江苏","name":"徐州","value":11}]},"2023-04":{"total":675,"province":[{"name":"浙江","value":113},{"name":"广东","value":93},{"name":"江苏","value":76},{"name":"上海","value":59},{"name":"四川","value":51},{"name":"北京","value":33},{"name":"福建","value":32},{"name":"安徽","value":29},{"name":"山东","value":25},{"name":"重庆","value":19},{"name":"湖北","value":19},{"name":"贵州","value":18},{"name":"湖南","value":18},{"name":"辽宁","value":18},{"name":"陕西","value":18},{"name":"河南","value":17},{"name":"天津","value":15},{"name":"广西","value":11},{"name":"黑龙江","value":11}],"city":[{"province":"上海","name":"上海","value":59},{"province":"四川","name":"成都","value":51},{"province":"江苏","name":"苏州","value":39},{"province":"广东","name":"深圳","value":37},{"province":"北京","name":"北京","value":33},{"province":"浙江","name":"杭州","value":33},{"province":"安徽","name":"合肥","value":29},{"province":"浙江","name":"宁波","value":28},{"province":"广东","name":"东莞","value":21},{"province":"广东","name":"广州","value":20},{"province":"重庆","name":"重庆","value":19},{"province":"湖北","name":"武汉","value":19},{"province":"贵州","name":"贵阳","value":18},{"province":"辽宁","name":"沈阳","value":18},{"province":"陕西","name":"西安","value":18},{"province":"湖南","name":"长沙","value":18},{"province":"福建","name":"泉州","value":17},{"province":"河南","name":"郑州","value":17},{"province":"浙江","name":"金华","value":16},{"province":"广东","name":"佛山","value":15},{"province":"福建","name":"厦门","value":15},{"province":"天津","name":"天津","value":15},{"province":"浙江","name":"嘉兴","value":14},{"province":"山东","name":"济南","value":13},{"province":"江苏","name":"南京","value":13},{"province":"江苏","name":"无锡","value":13},{"province":"山东","name":"青岛","value":12},{"province":"黑龙江","name":"哈尔滨","value":11},{"province":"广西","name":"南宁","value":11},{"province":"江苏","name":"南通","value":11},{"province":"浙江","name":"绍兴","value":11},{"province":"浙江","name":"温州","value":11}]},"2023-03":{"total":600,"province":[{"name":"江苏","value":100},{"name":"广东","value":92},{"name":"浙江","value":90},{"name":"上海","value":63},{"name":"四川","value":38},{"name":"北京","value":34},{"name":"辽宁","value":23},{"name":"山东","value":21},{"name":"陕西","value":20},{"name":"湖南","value":18},{"name":"重庆","value":14},{"name":"黑龙江","value":14},{"name":"福建","value":13},{"name":"云南","value":13},{"name":"安徽","value":12},{"name":"湖北","value":12},{"name":"天津","value":12},{"name":"广西","value":11}],"city":[{"province":"上海","name":"上海","value":63},{"province":"江苏","name":"苏州","value":48},{"province":"四川","name":"成都","value":38},{"province":"广东","name":"深圳","value":35},{"province":"北京","name":"北京","value":34},{"province":"浙江","name":"杭州","value":27},{"province":"江苏","name":"南京","value":25},{"province":"浙江","name":"宁波","value":25},{"province":"浙江","name":"嘉兴","value":24},{"province":"辽宁","name":"沈阳","value":23},{"province":"广东","name":"东莞","value":21},{"province":"广东","name":"广州","value":21},{"province":"山东","name":"青岛","value":21},{"province":"陕西","name":"西安","value":20},{"province":"湖南","name":"长沙","value":18},{"province":"广东","name":"佛山","value":15},{"province":"重庆","name":"重庆","value":14},{"province":"黑龙江","name":"哈尔滨","value":14},{"province":"浙江","name":"金华","value":14},{"province":"江苏","name":"无锡","value":14},{"province":"云南","name":"昆明","value":13},{"province":"江苏","name":"南通","value":13},{"province":"福建","name":"厦门","value":13},{"province":"安徽","name":"合肥","value":12},{"province":"天津","name":"天津","value":12},{"province":"湖北","name":"武汉","value":12},{"province":"广西","name":"南宁","value":11}]},"2023-02":{"total":461,"province":[{"name":"广东","value":77},{"name":"江苏","value":72},{"name":"浙江","value":52},{"name":"上海","value":48},{"name":"安徽","value":30},{"name":"四川","value":25},{"name":"北京","value":24},{"name":"福建","value":23},{"name":"陕西","value":20},{"name":"湖北","value":17},{"name":"重庆","value":15},{"name":"湖南","value":13},{"name":"天津","value":12},{"name":"广西","value":11},{"name":"江西","value":11},{"name":"山东","value":11}],"city":[{"province":"上海","name":"上海","value":48},{"province":"江苏","name":"苏州","value":37},{"province":"安徽","name":"合肥","value":30},{"province":"广东","name":"深圳","value":29},{"province":"浙江","name":"杭州","value":28},{"province":"四川","name":"成都","value":25},{"province":"北京","name":"北京","value":24},{"province":"浙江","name":"宁波","value":24},{"province":"江苏","name":"南京","value":23},{"province":"广东","name":"广州","value":20},{"province":"陕西","name":"西安","value":20},{"province":"广东","name":"东莞","value":17},{"province":"湖北","name":"武汉","value":17},{"province":"重庆","name":"重庆","value":15},{"province":"湖南","name":"长沙","value":13},{"province":"江苏","name":"南通","value":12},{"province":"福建","name":"泉州","value":12},{"province":"天津","name":"天津","value":12},{"province":"广东","name":"佛山","value":11},{"province":"福建","name":"福州","value":11},{"province":"江西","name":"南昌","value":11},{"province":"广西","name":"南宁","value":11},{"province":"山东","name":"青岛","value":11}]},"2023-01":{"total":249,"province":[{"name":"广东","value":67},{"name":"江苏","value":32},{"name":"上海","value":31},{"name":"四川","value":27},{"name":"北京","value":18},{"name":"重庆","value":14},{"name":"广西","value":14},{"name":"安徽","value":13},{"name":"湖北","value":11},{"name":"陕西","value":11},{"name":"浙江","value":11}],"city":[{"province":"上海","name":"上海","value":31},{"province":"四川","name":"成都","value":27},{"province":"广东","name":"深圳","value":23},{"province":"江苏","name":"苏州","value":21},{"province":"广东","name":"东莞","value":19},{"province":"北京","name":"北京","value":18},{"province":"重庆","name":"重庆","value":14},{"province":"广西","name":"南宁","value":14},{"province":"广东","name":"广州","value":13},{"province":"安徽","name":"合肥","value":13},{"province":"广东","name":"佛山","value":12},{"province":"江苏","name":"南京","value":11},{"province":"浙江","name":"绍兴","value":11},{"province":"湖北","name":"武汉","value":11},{"province":"陕西","name":"西安","value":11}]},"2022-12":{"total":928,"province":[{"name":"江苏","value":151},{"name":"浙江","value":143},{"name":"广东","value":108},{"name":"上海","value":88},{"name":"四川","value":62},{"name":"北京","value":54},{"name":"山东","value":43},{"name":"安徽","value":38},{"name":"湖北","value":35},{"name":"湖南","value":29},{"name":"重庆","value":28},{"name":"陕西","value":28},{"name":"河南","value":22},{"name":"贵州","value":18},{"name":"天津","value":16},{"name":"辽宁","value":15},{"name":"福建","value":14},{"name":"广西","value":14},{"name":"河北","value":11},{"name":"黑龙江","value":11}],"city":[{"province":"上海","name":"上海","value":88},{"province":"江苏","name":"苏州","value":70},{"province":"四川","name":"成都","value":62},{"province":"北京","name":"北京","value":54},{"province":"江苏","name":"南京","value":42},{"province":"安徽","name":"合肥","value":38},{"province":"浙江","name":"杭州","value":36},{"province":"湖北","name":"武汉","value":35},{"province":"浙江","name":"宁波","value":33},{"province":"广东","name":"广州","value":32},{"province":"广东","name":"深圳","value":31},{"province":"湖南","name":"长沙","value":29},{"province":"重庆","name":"重庆","value":28},{"province":"陕西","name":"西安","value":28},{"province":"山东","name":"青岛","value":24},{"province":"广东","name":"东莞","value":23},{"province":"河南","name":"郑州","value":22},{"province":"江苏","name":"南通","value":20},{"province":"山东","name":"济南","value":19},{"province":"江苏","name":"无锡","value":19},{"province":"贵州","name":"贵阳","value":18},{"province":"浙江","name":"温州","value":17},{"province":"浙江","name":"嘉兴","value":16},{"province":"浙江","name":"金华","value":16},{"province":"天津","name":"天津","value":16},{"province":"辽宁","name":"沈阳","value":15},{"province":"广西","name":"南宁","value":14},{"province":"福建","name":"泉州","value":14},{"province":"浙江","name":"绍兴","value":14},{"province":"广东","name":"佛山","value":11},{"province":"黑龙江","name":"哈尔滨","value":11},{"province":"浙江","name":"湖州","value":11},{"province":"河北","name":"石家庄","value":11},{"province":"广东","name":"中山","value":11}]},"2022-11":{"total":616,"province":[{"name":"浙江","value":128},{"name":"江苏","value":100},{"name":"广东","value":87},{"name":"上海","value":70},{"name":"四川","value":32},{"name":"山东","value":30},{"name":"安徽","value":23},{"name":"北京","value":22},{"name":"湖南","value":20},{"name":"江西","value":18},{"name":"陕西","value":18},{"name":"福建","value":15},{"name":"湖北","value":15},{"name":"贵州","value":13},{"name":"辽宁","value":13},{"name":"天津","value":12}],"city":[{"province":"上海","name":"上海","value":70},{"province":"浙江","name":"杭州","value":57},{"province":"江苏","name":"苏州","value":51},{"province":"江苏","name":"南京","value":36},{"province":"广东","name":"深圳","value":34},{"province":"四川","name":"成都","value":32},{"province":"浙江","name":"宁波","value":32},{"province":"安徽","name":"合肥","value":23},{"province":"北京","name":"北京","value":22},{"province":"广东","name":"佛山","value":21},{"province":"湖南","name":"长沙","value":20},{"province":"广东","name":"东莞","value":18},{"province":"江西","name":"南昌","value":18},{"province":"山东","name":"青岛","value":18},{"province":"陕西","name":"西安","value":18},{"province":"浙江","name":"绍兴","value":16},{"province":"福建","name":"厦门","value":15},{"province":"湖北","name":"武汉","value":15},{"province":"广东","name":"广州","value":14},{"province":"辽宁","name":"大连","value":13},{"province":"贵州","name":"贵阳","value":13},{"province":"江苏","name":"南通","value":13},{"province":"山东","name":"济南","value":12},{"province":"浙江","name":"嘉兴","value":12},{"province":"天津","name":"天津","value":12},{"province":"浙江","name":"温州","value":11}]},"2022-10":{"total":578,"province":[{"name":"浙江","value":103},{"name":"广东","value":97},{"name":"江苏","value":62},{"name":"北京","value":42},{"name":"上海","value":42},{"name":"四川","value":41},{"name":"山东","value":32},{"name":"辽宁","value":30},{"name":"重庆","value":26},{"name":"湖北","value":24},{"name":"安徽","value":18},{"name":"广西","value":18},{"name":"湖南","value":17},{"name":"天津","value":15},{"name":"福建","value":11}],"city":[{"province":"北京","name":"北京","value":42},{"province":"上海","name":"上海","value":42},{"province":"四川","name":"成都","value":41},{"province":"广东","name":"深圳","value":39},{"province":"浙江","name":"杭州","value":34},{"province":"江苏","name":"苏州","value":33},{"province":"重庆","name":"重庆","value":26},{"province":"湖北","name":"武汉","value":24},{"province":"广东","name":"东莞","value":22},{"province":"广东","name":"广州","value":21},{"province":"安徽","name":"合肥","value":18},{"province":"广西","name":"南宁","value":18},{"province":"江苏","name":"南京","value":17},{"province":"浙江","name":"宁波","value":17},{"province":"湖南","name":"长沙","value":17},{"province":"山东","name":"济南","value":16},{"province":"山东","name":"青岛","value":16},{"province":"辽宁","name":"大连","value":15},{"province":"广东","name":"佛山","value":15},{"province":"辽宁","name":"沈阳","value":15},{"province":"天津","name":"天津","value":15},{"province":"浙江","name":"温州","value":15},{"province":"浙江","name":"金华","value":13},{"province":"浙江","name":"绍兴","value":13},{"province":"江苏","name":"无锡","value":12},{"province":"浙江","name":"嘉兴","value":11},{"province":"福建","name":"泉州","value":11}]},"2022-09":{"total":750,"province":[{"name":"江苏","value":129},{"name":"浙江","value":119},{"name":"广东","value":105},{"name":"上海","value":81},{"name":"北京","value":41},{"name":"福建","value":41},{"name":"湖北","value":35},{"name":"山东","value":30},{"name":"陕西","value":29},{"name":"湖南","value":25},{"name":"重庆","value":24},{"name":"安徽","value":20},{"name":"四川","value":20},{"name":"天津","value":19},{"name":"广西","value":18},{"name":"河南","value":14}],"city":[{"province":"上海","name":"上海","value":81},{"province":"江苏","name":"苏州","value":60},{"province":"浙江","name":"杭州","value":52},{"province":"北京","name":"北京","value":41},{"province":"江苏","name":"南京","value":39},{"province":"广东","name":"深圳","value":35},{"province":"湖北","name":"武汉","value":35},{"province":"陕西","name":"西安","value":29},{"province":"广东","name":"广州","value":27},{"province":"湖南","name":"长沙","value":25},{"province":"重庆","name":"重庆","value":24},{"province":"广东","name":"东莞","value":23},{"province":"四川","name":"成都","value":20},{"province":"广东","name":"佛山","value":20},{"province":"安徽","name":"合肥","value":20},{"province":"浙江","name":"绍兴","value":20},{"province":"天津","name":"天津","value":19},{"province":"广西","name":"南宁","value":18},{"province":"浙江","name":"嘉兴","value":17},{"province":"浙江","name":"宁波","value":17},{"province":"江苏","name":"无锡","value":17},{"province":"山东","name":"济南","value":15},{"province":"山东","name":"青岛","value":15},{"province":"福建","name":"厦门","value":15},{"province":"福建","name":"福州","value":14},{"province":"河南","name":"郑州","value":14},{"province":"浙江","name":"金华","value":13},{"province":"江苏","name":"南通","value":13},{"province":"福建","name":"泉州","value":12}]},"2022-08":{"total":647,"province":[{"name":"江苏","value":108},{"name":"浙江","value":80},{"name":"广东","value":79},{"name":"上海","value":58},{"name":"四川","value":46},{"name":"北京","value":39},{"name":"辽宁","value":30},{"name":"安徽","value":26},{"name":"湖北","value":26},{"name":"山东","value":26},{"name":"陕西","value":23},{"name":"福建","value":21},{"name":"广西","value":19},{"name":"湖南","value":18},{"name":"天津","value":14},{"name":"重庆","value":12},{"name":"贵州","value":11},{"name":"河南","value":11}],"city":[{"province":"上海","name":"上海","value":58},{"province":"江苏","name":"苏州","value":56},{"province":"四川","name":"成都","value":46},{"province":"北京","name":"北京","value":39},{"province":"浙江","name":"杭州","value":36},{"province":"江苏","name":"南京","value":34},{"province":"安徽","name":"合肥","value":26},{"province":"湖北","name":"武汉","value":26},{"province":"广东","name":"深圳","value":23},{"province":"陕西","name":"西安","value":23},{"province":"福建","name":"福州","value":21},{"province":"广东","name":"广州","value":21},{"province":"广西","name":"南宁","value":19},{"province":"浙江","name":"宁波","value":19},{"province":"广东","name":"东莞","value":18},{"province":"江苏","name":"无锡","value":18},{"province":"湖南","name":"长沙","value":18},{"province":"广东","name":"佛山","value":17},{"province":"辽宁","name":"沈阳","value":17},{"province":"山东","name":"青岛","value":15},{"province":"天津","name":"天津","value":14},{"province":"辽宁","name":"大连","value":13},{"province":"浙江","name":"嘉兴","value":13},{"province":"重庆","name":"重庆","value":12},{"province":"浙江","name":"绍兴","value":12},{"province":"贵州","name":"贵阳","value":11},{"province":"山东","name":"济南","value":11},{"province":"河南","name":"郑州","value":11}]},"2022-07":{"total":580,"province":[{"name":"江苏","value":79},{"name":"浙江","value":75},{"name":"广东","value":67},{"name":"上海","value":67},{"name":"四川","value":51},{"name":"北京","value":46},{"name":"重庆","value":35},{"name":"湖北","value":24},{"name":"湖南","value":24},{"name":"安徽","value":21},{"name":"陕西","value":18},{"name":"山东","value":17},{"name":"福建","value":16},{"name":"贵州","value":15},{"name":"河南","value":13},{"name":"天津","value":12}],"city":[{"province":"上海","name":"上海","value":67},{"province":"四川","name":"成都","value":51},{"province":"江苏","name":"苏州","value":51},{"province":"北京","name":"北京","value":46},{"province":"重庆","name":"重庆","value":35},{"province":"浙江","name":"杭州","value":33},{"province":"浙江","name":"宁波","value":30},{"province":"江苏","name":"南京","value":28},{"province":"湖北","name":"武汉","value":24},{"province":"湖南","name":"长沙","value":24},{"province":"广东","name":"深圳","value":23},{"province":"安徽","name":"合肥","value":21},{"province":"陕西","name":"西安","value":18},{"province":"山东","name":"青岛","value":17},{"province":"福建","name":"厦门","value":16},{"province":"广东","name":"佛山","value":15},{"province":"广东","name":"广州","value":15},{"province":"贵州","name":"贵阳","value":15},{"province":"广东","name":"东莞","value":14},{"province":"河南","name":"郑州","value":13},{"province":"浙江","name":"绍兴","value":12},{"province":"天津","name":"天津","value":12}]},"2022-06":{"total":884,"province":[{"name":"江苏","value":152},{"name":"浙江","value":149},{"name":"广东","value":104},{"name":"上海","value":78},{"name":"四川","value":57},{"name":"山东","value":43},{"name":"福建","value":38},{"name":"湖北","value":36},{"name":"河南","value":31},{"name":"北京","value":29},{"name":"安徽","value":26},{"name":"湖南","value":26},{"name":"陕西","value":24},{"name":"辽宁","value":21},{"name":"天津","value":21},{"name":"重庆","value":19},{"name":"广西","value":16},{"name":"云南","value":14}],"city":[{"province":"上海","name":"上海","value":78},{"province":"江苏","name":"苏州","value":62},{"province":"四川","name":"成都","value":57},{"province":"浙江","name":"杭州","value":42},{"province":"广东","name":"深圳","value":36},{"province":"湖北","name":"武汉","value":36},{"province":"江苏","name":"南京","value":35},{"province":"广东","name":"广州","value":32},{"province":"河南","name":"郑州","value":31},{"province":"北京","name":"北京","value":29},{"province":"浙江","name":"绍兴","value":28},{"province":"安徽","name":"合肥","value":26},{"province":"山东","name":"青岛","value":26},{"province":"湖南","name":"长沙","value":26},{"province":"广东","name":"东莞","value":25},{"province":"陕西","name":"西安","value":24},{"province":"江苏","name":"无锡","value":23},{"province":"江苏","name":"南通","value":21},{"province":"浙江","name":"宁波","value":21},{"province":"辽宁","name":"沈阳","value":21},{"province":"天津","name":"天津","value":21},{"province":"重庆","name":"重庆","value":19},{"province":"山东","name":"济南","value":17},{"province":"浙江","name":"嘉兴","value":17},{"province":"浙江","name":"金华","value":17},{"province":"广西","name":"南宁","value":16},{"province":"云南","name":"昆明","value":14},{"province":"福建","name":"泉州","value":14},{"province":"福建","name":"福州","value":13},{"province":"浙江","name":"台州","value":13},{"province":"江苏","name":"常州","value":11},{"province":"广东","name":"佛山","value":11},{"province":"福建","name":"厦门","value":11},{"province":"浙江","name":"温州","value":11}]}}